circDraw/__init__.py
circDraw/__main__.py
circDraw/circDraw.py
circDraw/draw.py
circDraw/version.py
circDraw_upload/__init__.py
circDraw_upload/__main__.py
circDraw_upload/upload.py
circDraw_upload/version.py
circDraw-0.1.0.dist-info/LICENSE
circDraw-0.1.0.dist-info/METADATA
circDraw-0.1.0.dist-info/WHEEL
circDraw-0.1.0.dist-info/entry_points.txt
circDraw-0.1.0.dist-info/top_level.txt
circDraw-0.1.0.dist-info/RECORD
