Metadata-Version: 2.1
Name: circDraw
Version: 0.1.0
Summary: A python package for circDraw visualization and server command line interface
Home-page: https://github.com/Mr-Milk/circDraw-py
Author: Yimin Zheng, Tianqin Li
Author-email: zym.zym1220@gmail.com, jacklitianqin@gmail.com
License: UNKNOWN
Platform: UNKNOWN
Classifier: Programming Language :: Python :: 3
Classifier: License :: OSI Approved :: MIT License
Classifier: Operating System :: OS Independent
Requires-Dist: numpy
Requires-Dist: matplotlib
Requires-Dist: colour
Requires-Dist: requests
